s3tethys/__init__.py
s3tethys/main.py
s3tethys/utils.py
s3tethys/datasets/__init__.py
s3tethys/tests/__init__.py
s3tethys/tests/utest_s3tethys.py
s3tethys-0.1.4.dist-info/METADATA
s3tethys-0.1.4.dist-info/WHEEL
s3tethys-0.1.4.dist-info/licenses/LICENSE
s3tethys-0.1.4.dist-info/RECORD
